imediff/__init__.py
imediff/cli.py
imediff/config.py
imediff/diff3lib.py
imediff/initialize_args.py
imediff/initialize_confs.py
imediff/install.py
imediff/lines2lib.py
imediff/main.py
imediff/safe_curses.py
imediff/tui.py
imediff/utils.py
imediff/data/git-ime.1
imediff/data/git-ime.in
imediff/data/imediff
imediff/data/imediff.1
imediff-3.4.0.dist-info/AUTHORS
imediff-3.4.0.dist-info/LICENSE
imediff-3.4.0.dist-info/METADATA
imediff-3.4.0.dist-info/WHEEL
imediff-3.4.0.dist-info/entry_points.txt
imediff-3.4.0.dist-info/top_level.txt
imediff-3.4.0.dist-info/RECORD
