Metadata-Version: 2.2
Name: imediff
Version: 3.4.0
Summary: 2-way/3-way merge tool (CLI, Ncurses)
Author-email: Osamu Aoki <osamu@debian.org>, Jarno Elonen <elonen@iki.fi>
Maintainer-email: Osamu Aoki <osamu@debian.org>
License: 		    GNU GENERAL PUBLIC LICENSE
Project-URL: Homepage, https://github.com/osamuaoki/imediff
Project-URL: Bug Reports, https://github.com/osamuaoki/imediff/issues
Project-URL: Source, https://github.com/osamuaoki/imediff/
Keywords: imediff,merge,diff,cli,ncurses,git-ime,ime
Classifier: Development Status :: 5 - Production/Stable
Classifier: Intended Audience :: Developers
Classifier: Topic :: Text Processing :: General
Classifier: License :: OSI Approved :: GNU General Public License v2 or later (GPLv2+)
Classifier: Programming Language :: Python :: 3
Classifier: Programming Language :: Python :: 3.9
Classifier: Programming Language :: Python :: 3.10
Classifier: Programming Language :: Python :: 3.11
Classifier: Programming Language :: Python :: 3.12
Classifier: Programming Language :: Python :: 3.13
Classifier: Programming Language :: Python :: 3 :: Only
Classifier: Environment :: Console :: Curses
Classifier: Operating System :: POSIX :: Linux
Requires-Python: >=3.9
License-File: LICENSE
License-File: AUTHORS
Provides-Extra: dev
Requires-Dist: check-manifest; extra == "dev"
